<?xml version="1.0"?>
<trafficlist>
    <aircraft>
        <model>Aircraft/A332/A332-KoreanAir.xml</model>
        <livery>KAL</livery>
        <airline>KAL</airline>
        <home-port>RKSI</home-port>
        <required-aircraft>A330KAL</required-aircraft>
        <actype>A330-322</actype>
        <offset>9</offset>
        <radius>39</radius>
        <flighttype>gate</flighttype>
        <performance-class>jet_transport</performance-class>
        <registration>HL7550</registration>
        <heavy>true</heavy>
    </aircraft>
    <aircraft>
        <model>Aircraft/A332/A332-KoreanAir.xml</model>
        <livery>KAL</livery>
        <airline>KAL</airline>
        <home-port>RKSI</home-port>
        <required-aircraft>A330KAL</required-aircraft>
        <actype>A330-322</actype>
        <offset>9</offset>
        <radius>39</radius>
        <flighttype>gate</flighttype>
        <performance-class>jet_transport</performance-class>
        <registration>HL7551</registration>
        <heavy>true</heavy>
    </aircraft>
    <aircraft>
        <model>Aircraft/A332/A332-KoreanAir.xml</model>
        <livery>KAL</livery>
        <airline>KAL</airline>
        <home-port>RKSI</home-port>
        <required-aircraft>A330KAL</required-aircraft>
        <actype>A330-322</actype>
        <offset>9</offset>
        <radius>39</radius>
        <flighttype>gate</flighttype>
        <performance-class>jet_transport</performance-class>
        <registration>HL7524</registration>
        <heavy>true</heavy>
    </aircraft>
    <aircraft>
        <model>Aircraft/A332/A332-KoreanAir.xml</model>
        <livery>KAL</livery>
        <airline>KAL</airline>
        <home-port>RKSI</home-port>
        <required-aircraft>A330KAL</required-aircraft>
        <actype>A330-322</actype>
        <offset>9</offset>
        <radius>39</radius>
        <flighttype>gate</flighttype>
        <performance-class>jet_transport</performance-class>
        <registration>HL7525</registration>
        <heavy>true</heavy>
    </aircraft>
    <aircraft>
        <model>Aircraft/A332/A332-KoreanAir.xml</model>
        <livery>KAL</livery>
        <airline>KAL</airline>
        <home-port>RKSI</home-port>
        <required-aircraft>A330KAL</required-aircraft>
        <actype>A330-223</actype>
        <offset>9</offset>
        <radius>39</radius>
        <flighttype>gate</flighttype>
        <performance-class>jet_transport</performance-class>
        <registration>HL7538</registration>
        <heavy>true</heavy>
    </aircraft>
    <aircraft>
        <model>Aircraft/A332/A332-KoreanAir.xml</model>
        <livery>KAL</livery>
        <airline>KAL</airline>
        <home-port>RKSI</home-port>
        <required-aircraft>A330KAL</required-aircraft>
        <actype>A330-222</actype>
        <offset>9</offset>
        <radius>39</radius>
        <flighttype>gate</flighttype>
        <performance-class>jet_transport</performance-class>
        <registration>HL7539</registration>
        <heavy>true</heavy>
    </aircraft>
    <aircraft>
        <model>Aircraft/A332/A332-KoreanAir.xml</model>
        <livery>KAL</livery>
        <airline>KAL</airline>
        <home-port>RKSI</home-port>
        <required-aircraft>A330KAL</required-aircraft>
        <actype>A330-322</actype>
        <offset>9</offset>
        <radius>39</radius>
        <flighttype>gate</flighttype>
        <performance-class>jet_transport</performance-class>
        <registration>HL7540</registration>
        <heavy>true</heavy>
    </aircraft>
    <aircraft>
        <model>Aircraft/A332/A332-KoreanAir.xml</model>
        <livery>KAL</livery>
        <airline>KAL</airline>
        <home-port>RKSI</home-port>
        <required-aircraft>A330KAL</required-aircraft>
        <actype>A330-323X</actype>
        <offset>9</offset>
        <radius>39</radius>
        <flighttype>gate</flighttype>
        <performance-class>jet_transport</performance-class>
        <registration>HL7554</registration>
        <heavy>true</heavy>
    </aircraft>
    <aircraft>
        <model>Aircraft/A332/A332-KoreanAir.xml</model>
        <livery>KAL</livery>
        <airline>KAL</airline>
        <home-port>RKSI</home-port>
        <required-aircraft>A330KAL</required-aircraft>
        <actype>A330-223</actype>
        <offset>9</offset>
        <radius>39</radius>
        <flighttype>gate</flighttype>
        <performance-class>jet_transport</performance-class>
        <registration>HL7552</registration>
        <heavy>true</heavy>
    </aircraft>
    <aircraft>
        <model>Aircraft/A332/A332-KoreanAir.xml</model>
        <livery>KAL</livery>
        <airline>KAL</airline>
        <home-port>RKSI</home-port>
        <required-aircraft>A330KAL</required-aircraft>
        <actype>A330-323X</actype>
        <offset>9</offset>
        <radius>39</radius>
        <flighttype>gate</flighttype>
        <performance-class>jet_transport</performance-class>
        <registration>HL7553</registration>
        <heavy>true</heavy>
    </aircraft>
    <aircraft>
        <model>Aircraft/A332/A332-KoreanAir.xml</model>
        <livery>KAL</livery>
        <airline>KAL</airline>
        <home-port>RKSI</home-port>
        <required-aircraft>A330KAL</required-aircraft>
        <actype>A330-323X</actype>
        <offset>9</offset>
        <radius>39</radius>
        <flighttype>gate</flighttype>
        <performance-class>jet_transport</performance-class>
        <registration>HL7584</registration>
        <heavy>true</heavy>
    </aircraft>
    <aircraft>
        <model>Aircraft/A332/A332-KoreanAir.xml</model>
        <livery>KAL</livery>
        <airline>KAL</airline>
        <home-port>RKSI</home-port>
        <required-aircraft>A330KAL</required-aircraft>
        <actype>A330-323X</actype>
        <offset>9</offset>
        <radius>39</radius>
        <flighttype>gate</flighttype>
        <performance-class>jet_transport</performance-class>
        <registration>HL7585</registration>
        <heavy>true</heavy>
    </aircraft>
    <aircraft>
        <model>Aircraft/A332/A332-KoreanAir.xml</model>
        <livery>KAL</livery>
        <airline>KAL</airline>
        <home-port>RKSI</home-port>
        <required-aircraft>A330KAL</required-aircraft>
        <actype>A330-323X</actype>
        <offset>9</offset>
        <radius>39</radius>
        <flighttype>gate</flighttype>
        <performance-class>jet_transport</performance-class>
        <registration>HL7586</registration>
        <heavy>true</heavy>
    </aircraft>
    <aircraft>
        <model>Aircraft/A332/A332-KoreanAir.xml</model>
        <livery>KAL</livery>
        <airline>KAL</airline>
        <home-port>RKSI</home-port>
        <required-aircraft>A330KAL</required-aircraft>
        <actype>A330-323X</actype>
        <offset>9</offset>
        <radius>39</radius>
        <flighttype>gate</flighttype>
        <performance-class>jet_transport</performance-class>
        <registration>HL7487</registration>
        <heavy>true</heavy>
    </aircraft>
    <aircraft>
        <model>Aircraft/A332/A332-KoreanAir.xml</model>
        <livery>KAL</livery>
        <airline>KAL</airline>
        <home-port>RKSI</home-port>
        <required-aircraft>A330KAL</required-aircraft>
        <actype>A330-323X</actype>
        <offset>9</offset>
        <radius>39</radius>
        <flighttype>gate</flighttype>
        <performance-class>jet_transport</performance-class>
        <registration>HL7701</registration>
        <heavy>true</heavy>
    </aircraft>
    <aircraft>
        <model>Aircraft/A332/A332-KoreanAir.xml</model>
        <livery>KAL</livery>
        <airline>KAL</airline>
        <home-port>RKSI</home-port>
        <required-aircraft>A330KAL</required-aircraft>
        <actype>A330-323X</actype>
        <offset>9</offset>
        <radius>39</radius>
        <flighttype>gate</flighttype>
        <performance-class>jet_transport</performance-class>
        <registration>HL7702</registration>
        <heavy>true</heavy>
    </aircraft>
    <aircraft>
        <model>Aircraft/A332/A332-KoreanAir.xml</model>
        <livery>KAL</livery>
        <airline>KAL</airline>
        <home-port>RKSI</home-port>
        <required-aircraft>A330KAL</required-aircraft>
        <actype>A330-323X</actype>
        <offset>9</offset>
        <radius>39</radius>
        <flighttype>gate</flighttype>
        <performance-class>jet_transport</performance-class>
        <registration>HL7709</registration>
        <heavy>true</heavy>
    </aircraft>
    <aircraft>
        <model>Aircraft/A332/A332-KoreanAir.xml</model>
        <livery>KAL</livery>
        <airline>KAL</airline>
        <home-port>RKSI</home-port>
        <required-aircraft>A330KAL</required-aircraft>
        <actype>A330-323X</actype>
        <offset>9</offset>
        <radius>39</radius>
        <flighttype>gate</flighttype>
        <performance-class>jet_transport</performance-class>
        <registration>HL7710</registration>
        <heavy>true</heavy>
    </aircraft>
    <aircraft>
        <model>Aircraft/A332/A332-KoreanAir.xml</model>
        <livery>KAL</livery>
        <airline>KAL</airline>
        <home-port>RKSI</home-port>
        <required-aircraft>A330KAL</required-aircraft>
        <actype>A330-332</actype>
        <offset>9</offset>
        <radius>39</radius>
        <flighttype>gate</flighttype>
        <performance-class>jet_transport</performance-class>
        <registration>HL7720</registration>
        <heavy>true</heavy>
    </aircraft>
        <flight>
            <callsign>KoreanAir0925</callsign>
            <required-aircraft>A330KAL</required-aircraft>
            <fltrules>IFR</fltrules>
            <departure>
                <port>RKSI</port>
                <time>3/02:00:00</time>
            </departure>
            <cruise-alt>360</cruise-alt>
            <arrival>
                <port>EHAM</port>
                <time>3/13:50:00</time>
            </arrival>
            <repeat>WEEK</repeat>
        </flight>
        <flight>
            <callsign>KoreanAir0925</callsign>
            <required-aircraft>A330KAL</required-aircraft>
            <fltrules>IFR</fltrules>
            <departure>
                <port>RKSI</port>
                <time>5/02:00:00</time>
            </departure>
            <cruise-alt>360</cruise-alt>
            <arrival>
                <port>EHAM</port>
                <time>5/13:50:00</time>
            </arrival>
            <repeat>WEEK</repeat>
        </flight>
        <flight>
            <callsign>KoreanAir0925</callsign>
            <required-aircraft>A330KAL</required-aircraft>
            <fltrules>IFR</fltrules>
            <departure>
                <port>RKSI</port>
                <time>0/02:00:00</time>
            </departure>
            <cruise-alt>360</cruise-alt>
            <arrival>
                <port>EHAM</port>
                <time>0/13:50:00</time>
            </arrival>
            <repeat>WEEK</repeat>
        </flight>
        <flight>
            <callsign>KoreanAir0926</callsign>
            <required-aircraft>A330KAL</required-aircraft>
            <fltrules>IFR</fltrules>
            <departure>
                <port>EHAM</port>
                <time>3/16:10:00</time>
            </departure>
            <cruise-alt>360</cruise-alt>
            <arrival>
                <port>RKSI</port>
                <time>4/02:55:00</time>
            </arrival>
            <repeat>WEEK</repeat>
        </flight>
        <flight>
            <callsign>KoreanAir0926</callsign>
            <required-aircraft>A330KAL</required-aircraft>
            <fltrules>IFR</fltrules>
            <departure>
                <port>EHAM</port>
                <time>5/16:10:00</time>
            </departure>
            <cruise-alt>360</cruise-alt>
            <arrival>
                <port>RKSI</port>
                <time>6/02:55:00</time>
            </arrival>
            <repeat>WEEK</repeat>
        </flight>
        <flight>
            <callsign>KoreanAir0926</callsign>
            <required-aircraft>A330KAL</required-aircraft>
            <fltrules>IFR</fltrules>
            <departure>
                <port>EHAM</port>
                <time>0/16:10:00</time>
            </departure>
            <cruise-alt>360</cruise-alt>
            <arrival>
                <port>RKSI</port>
                <time>1/02:55:00</time>
            </arrival>
            <repeat>WEEK</repeat>
        </flight>
        <!--RKSI-YSSY-RKSI-->
        <flight>
            <callsign>KE-121</callsign>
            <required-aircraft>A330KAL</required-aircraft>
            <fltrules>IFR</fltrules>
            <departure>
                <port>RKSI</port>
                <time>09:05:00</time>
            </departure>
            <cruise-alt>360</cruise-alt>
            <arrival>
                <port>YSSY</port>
                <time>20:30:00</time>
            </arrival>
            <repeat>24Hr</repeat>
        </flight>
        <flight>
            <callsign>KE-122</callsign>
            <required-aircraft>A330KAL</required-aircraft>
            <fltrules>IFR</fltrules>
            <departure>
                <port>YSSY</port>
                <time>21:55:00</time>
            </departure>
            <cruise-alt>360</cruise-alt>
            <arrival>
                <port>RKSI</port>
                <time>09:25:00</time>
            </arrival>
            <repeat>24Hr</repeat>
        </flight>
</trafficlist>
